<VirtualOutCmd Title='Standby' Comment='' CmdOnMethod='GET' CmdOffMethod='GET' CmdOn='\x00\x00\x02\x00\x0f\x00\x00\x00\x00\x02\x32\x30' CmdOnHTTP='' CmdOnPost='' CmdOff='' CmdOffHTTP='' CmdOffPost='' Analog='false' Repeat='0' RepeatRate='0'/>
<VirtualOutCmd Title='Standby Timer 15min.' Comment='' CmdOnMethod='GET' CmdOffMethod='GET' CmdOn='\x00\x00\x02\x00\x0f\x00\x00\x00\x00\x04\x32\x39\x30\x30' CmdOnHTTP='' CmdOnPost='' CmdOff='' CmdOffHTTP='' CmdOffPost='' Analog='false' Repeat='0' RepeatRate='0'/>
<VirtualOutCmd Title='Standby Timer 30min.' Comment='' CmdOnMethod='GET' CmdOffMethod='GET' CmdOn='\x00\x00\x02\x00\x0f\x00\x00\x00\x00\x05\x32\x31\x38\x30\x30' CmdOnHTTP='' CmdOnPost='' CmdOff='' CmdOffHTTP='' CmdOffPost='' Analog='false' Repeat='0' RepeatRate='0'/>
<VirtualOutCmd Title='Standby Timer 60min.' Comment='' CmdOnMethod='GET' CmdOffMethod='GET' CmdOn='\x00\x00\x02\x00\x0f\x00\x00\x00\x00\x05\x32\x33\x36\x30\x30' CmdOnHTTP='' CmdOnPost='' CmdOff='' CmdOffHTTP='' CmdOffPost='' Analog='false' Repeat='0' RepeatRate='0'/>
<VirtualOutCmd Title='Standby Timer 120min.' Comment='' CmdOnMethod='GET' CmdOffMethod='GET' CmdOn='\x00\x00\x02\x00\x0f\x00\x00\x00\x00\x05\x32\x37\x32\x30\x30' CmdOnHTTP='' CmdOnPost='' CmdOff='' CmdOffHTTP='' CmdOffPost='' Analog='false' Repeat='0' RepeatRate='0'/>
<VirtualOutCmd Title='Standby Timer 180min.' Comment='' CmdOnMethod='GET' CmdOffMethod='GET' CmdOn='\x00\x00\x02\x00\x0f\x00\x00\x00\x00\x06\x32\x31\x30\x38\x30\x30' CmdOnHTTP='' CmdOnPost='' CmdOff='' CmdOffHTTP='' CmdOffPost='' Analog='false' Repeat='0' RepeatRate='0'/>
<VirtualOutCmd Title='Standby Timer abbrechen' Comment='' CmdOnMethod='GET' CmdOffMethod='GET' CmdOn='\x00\x00\x02\x00\x0f\x00\x00\x00\x00\x02\x46\x30' CmdOnHTTP='' CmdOnPost='' CmdOff='' CmdOffHTTP='' CmdOffPost='' Analog='false' Repeat='0' RepeatRate='0'/>
<VirtualOutCmd Title='Raum: Neutral' Comment='Neutrale Grundeinstellung' CmdOnMethod='GET' CmdOffMethod='GET' CmdOn='\x00\x00\x02\x02\x07\x00\x00\x00\x00\x07\x6e\x65\x75\x74\x72\x61\x6c' CmdOnHTTP='' CmdOnPost='' CmdOff='' CmdOffHTTP='' CmdOffPost='' Analog='false' Repeat='0' RepeatRate='0'/>
<VirtualOutCmd Title='Raum: Im Freien' Comment='Optimales Klangfeld, wenn das Produkt im Freien steht' CmdOnMethod='GET' CmdOffMethod='GET' CmdOn='\x00\x00\x02\x02\x07\x00\x00\x00\x00\x07\x6f\x75\x74\x64\x6f\x6f\x72' CmdOnHTTP='' CmdOnPost='' CmdOff='' CmdOffHTTP='' CmdOffPost='' Analog='false' Repeat='0' RepeatRate='0'/>
<VirtualOutCmd Title='Raum: Regal' Comment='Optimales Klangfeld, wenn das Produkt in einem Regal steht' CmdOnMethod='GET' CmdOffMethod='GET' CmdOn='\x00\x00\x02\x02\x07\x00\x00\x00\x00\x05\x73\x68\x65\x6c\x66' CmdOnHTTP='' CmdOnPost='' CmdOff='' CmdOffHTTP='' CmdOffPost='' Analog='false' Repeat='0' RepeatRate='0'/>
<VirtualOutCmd Title='Raum: Tisch' Comment='Optimales Klangfeld, wenn das Produkt auf einem Tisch steht' CmdOnMethod='GET' CmdOffMethod='GET' CmdOn='\x00\x00\x02\x02\x07\x00\x00\x00\x00\x05\x74\x61\x62\x6c\x65' CmdOnHTTP='' CmdOnPost='' CmdOff='' CmdOffHTTP='' CmdOffPost='' Analog='false' Repeat='0' RepeatRate='0'/>
<VirtualOutCmd Title='Raum: Boden' Comment='Optimales Klangfeld, wenn das Produkt auf dem Boden steht' CmdOnMethod='GET' CmdOffMethod='GET' CmdOn='\x00\x00\x02\x02\x07\x00\x00\x00\x00\x05\x66\x6c\x6f\x6f\x72' CmdOnHTTP='' CmdOnPost='' CmdOff='' CmdOffHTTP='' CmdOffPost='' Analog='false' Repeat='0' RepeatRate='0'/>
<VirtualOutCmd Title='LED immer an (on)' Comment='' CmdOnMethod='GET' CmdOffMethod='GET' CmdOn='\x00\x00\x02\x02\x65\x00\x00\x00\x00\x01\x30' CmdOnHTTP='' CmdOnPost='' CmdOff='' CmdOffHTTP='' CmdOffPost='' Analog='false' Repeat='0' RepeatRate='0'/>
<VirtualOutCmd Title='LED immer an (off)' Comment='' CmdOnMethod='GET' CmdOffMethod='GET' CmdOn='\x00\x00\x02\x02\x65\x00\x00\x00\x00\x01\x31' CmdOnHTTP='' CmdOnPost='' CmdOff='' CmdOffHTTP='' CmdOffPost='' Analog='false' Repeat='0' RepeatRate='0'/>
<VirtualOutCmd Title='LED Helligkeit V einstellig' Comment='' CmdOnMethod='GET' CmdOffMethod='GET' CmdOn='\x00\x00\x02\x01\x2d\x00\x00\x00\x00\x01&lt;v&gt;' CmdOnHTTP='' CmdOnPost='' CmdOff='' CmdOffHTTP='' CmdOffPost='' Analog='true' Repeat='0' RepeatRate='0'/>
<VirtualOutCmd Title='LED Helligkeit V zweistellig' Comment='' CmdOnMethod='GET' CmdOffMethod='GET' CmdOn='\x00\x00\x02\x01\x2d\x00\x00\x00\x00\x02&lt;v&gt;' CmdOnHTTP='' CmdOnPost='' CmdOff='' CmdOffHTTP='' CmdOffPost='' Analog='true' Repeat='0' RepeatRate='0'/>
<VirtualOutCmd Title='LED Helligkeit V dreistellig' Comment='' CmdOnMethod='GET' CmdOffMethod='GET' CmdOn='\x00\x00\x02\x01\x2d\x00\x00\x04\x00\x03&lt;v&gt;' CmdOnHTTP='' CmdOnPost='' CmdOff='' CmdOffHTTP='' CmdOffPost='' Analog='true' Repeat='0' RepeatRate='0'/>
<VirtualOutCmd Title='LED Helligkeit 0' Comment='' CmdOnMethod='GET' CmdOffMethod='GET' CmdOn='\x00\x00\x02\x01\x2d\x00\x00\x00\x00\x01\x30' CmdOnHTTP='' CmdOnPost='' CmdOff='' CmdOffHTTP='' CmdOffPost='' Analog='false' Repeat='0' RepeatRate='0'/>
<VirtualOutCmd Title='LED Helligkeit 1' Comment='' CmdOnMethod='GET' CmdOffMethod='GET' CmdOn='\x00\x00\x02\x01\x2d\x00\x00\x00\x00\x01\x31' CmdOnHTTP='' CmdOnPost='' CmdOff='' CmdOffHTTP='' CmdOffPost='' Analog='false' Repeat='0' RepeatRate='0'/>
<VirtualOutCmd Title='LED Helligkeit 2' Comment='' CmdOnMethod='GET' CmdOffMethod='GET' CmdOn='\x00\x00\x02\x01\x2d\x00\x00\x00\x00\x01\x32' CmdOnHTTP='' CmdOnPost='' CmdOff='' CmdOffHTTP='' CmdOffPost='' Analog='false' Repeat='0' RepeatRate='0'/>
<VirtualOutCmd Title='LED Helligkeit 3' Comment='' CmdOnMethod='GET' CmdOffMethod='GET' CmdOn='\x00\x00\x02\x01\x2d\x00\x00\x00\x00\x01\x33' CmdOnHTTP='' CmdOnPost='' CmdOff='' CmdOffHTTP='' CmdOffPost='' Analog='false' Repeat='0' RepeatRate='0'/>
<VirtualOutCmd Title='LED Helligkeit 4' Comment='' CmdOnMethod='GET' CmdOffMethod='GET' CmdOn='\x00\x00\x02\x01\x2d\x00\x00\x00\x00\x01\x34' CmdOnHTTP='' CmdOnPost='' CmdOff='' CmdOffHTTP='' CmdOffPost='' Analog='false' Repeat='0' RepeatRate='0'/>
<VirtualOutCmd Title='LED Helligkeit 5' Comment='' CmdOnMethod='GET' CmdOffMethod='GET' CmdOn='\x00\x00\x02\x01\x2d\x00\x00\x00\x00\x01\x35' CmdOnHTTP='' CmdOnPost='' CmdOff='' CmdOffHTTP='' CmdOffPost='' Analog='false' Repeat='0' RepeatRate='0'/>
<VirtualOutCmd Title='LED Helligkeit 6' Comment='' CmdOnMethod='GET' CmdOffMethod='GET' CmdOn='\x00\x00\x02\x01\x2d\x00\x00\x00\x00\x01\x36' CmdOnHTTP='' CmdOnPost='' CmdOff='' CmdOffHTTP='' CmdOffPost='' Analog='false' Repeat='0' RepeatRate='0'/>
<VirtualOutCmd Title='LED Helligkeit 7' Comment='' CmdOnMethod='GET' CmdOffMethod='GET' CmdOn='\x00\x00\x02\x01\x2d\x00\x00\x00\x00\x01\x37' CmdOnHTTP='' CmdOnPost='' CmdOff='' CmdOffHTTP='' CmdOffPost='' Analog='false' Repeat='0' RepeatRate='0'/>
<VirtualOutCmd Title='LED Helligkeit 8' Comment='' CmdOnMethod='GET' CmdOffMethod='GET' CmdOn='\x00\x00\x02\x01\x2d\x00\x00\x00\x00\x01\x38' CmdOnHTTP='' CmdOnPost='' CmdOff='' CmdOffHTTP='' CmdOffPost='' Analog='false' Repeat='0' RepeatRate='0'/>
<VirtualOutCmd Title='LED Helligkeit 9' Comment='' CmdOnMethod='GET' CmdOffMethod='GET' CmdOn='\x00\x00\x02\x01\x2d\x00\x00\x00\x00\x01\x39' CmdOnHTTP='' CmdOnPost='' CmdOff='' CmdOffHTTP='' CmdOffPost='' Analog='false' Repeat='0' RepeatRate='0'/>
<VirtualOutCmd Title='LED Helligkeit 10' Comment='' CmdOnMethod='GET' CmdOffMethod='GET' CmdOn='\x00\x00\x02\x01\x2d\x00\x00\x00\x00\x02\x31\x30' CmdOnHTTP='' CmdOnPost='' CmdOff='' CmdOffHTTP='' CmdOffPost='' Analog='false' Repeat='0' RepeatRate='0'/>
<VirtualOutCmd Title='LED Helligkeit 11' Comment='' CmdOnMethod='GET' CmdOffMethod='GET' CmdOn='\x00\x00\x02\x01\x2d\x00\x00\x00\x00\x02\x31\x31' CmdOnHTTP='' CmdOnPost='' CmdOff='' CmdOffHTTP='' CmdOffPost='' Analog='false' Repeat='0' RepeatRate='0'/>
<VirtualOutCmd Title='LED Helligkeit 12' Comment='' CmdOnMethod='GET' CmdOffMethod='GET' CmdOn='\x00\x00\x02\x01\x2d\x00\x00\x00\x00\x02\x31\x32' CmdOnHTTP='' CmdOnPost='' CmdOff='' CmdOffHTTP='' CmdOffPost='' Analog='false' Repeat='0' RepeatRate='0'/>
<VirtualOutCmd Title='LED Helligkeit 13' Comment='' CmdOnMethod='GET' CmdOffMethod='GET' CmdOn='\x00\x00\x02\x01\x2d\x00\x00\x00\x00\x02\x31\x33' CmdOnHTTP='' CmdOnPost='' CmdOff='' CmdOffHTTP='' CmdOffPost='' Analog='false' Repeat='0' RepeatRate='0'/>
<VirtualOutCmd Title='LED Helligkeit 14' Comment='' CmdOnMethod='GET' CmdOffMethod='GET' CmdOn='\x00\x00\x02\x01\x2d\x00\x00\x00\x00\x02\x31\x34' CmdOnHTTP='' CmdOnPost='' CmdOff='' CmdOffHTTP='' CmdOffPost='' Analog='false' Repeat='0' RepeatRate='0'/>
<VirtualOutCmd Title='LED Helligkeit 15' Comment='' CmdOnMethod='GET' CmdOffMethod='GET' CmdOn='\x00\x00\x02\x01\x2d\x00\x00\x00\x00\x02\x31\x35' CmdOnHTTP='' CmdOnPost='' CmdOff='' CmdOffHTTP='' CmdOffPost='' Analog='false' Repeat='0' RepeatRate='0'/>
<VirtualOutCmd Title='LED Helligkeit 16' Comment='' CmdOnMethod='GET' CmdOffMethod='GET' CmdOn='\x00\x00\x02\x01\x2d\x00\x00\x00\x00\x02\x31\x36' CmdOnHTTP='' CmdOnPost='' CmdOff='' CmdOffHTTP='' CmdOffPost='' Analog='false' Repeat='0' RepeatRate='0'/>
<VirtualOutCmd Title='LED Helligkeit 17' Comment='' CmdOnMethod='GET' CmdOffMethod='GET' CmdOn='\x00\x00\x02\x01\x2d\x00\x00\x00\x00\x02\x31\x37' CmdOnHTTP='' CmdOnPost='' CmdOff='' CmdOffHTTP='' CmdOffPost='' Analog='false' Repeat='0' RepeatRate='0'/>
<VirtualOutCmd Title='LED Helligkeit 18' Comment='' CmdOnMethod='GET' CmdOffMethod='GET' CmdOn='\x00\x00\x02\x01\x2d\x00\x00\x00\x00\x02\x31\x38' CmdOnHTTP='' CmdOnPost='' CmdOff='' CmdOffHTTP='' CmdOffPost='' Analog='false' Repeat='0' RepeatRate='0'/>
<VirtualOutCmd Title='LED Helligkeit 19' Comment='' CmdOnMethod='GET' CmdOffMethod='GET' CmdOn='\x00\x00\x02\x01\x2d\x00\x00\x00\x00\x02\x31\x39' CmdOnHTTP='' CmdOnPost='' CmdOff='' CmdOffHTTP='' CmdOffPost='' Analog='false' Repeat='0' RepeatRate='0'/>
<VirtualOutCmd Title='LED Helligkeit 20' Comment='' CmdOnMethod='GET' CmdOffMethod='GET' CmdOn='\x00\x00\x02\x01\x2d\x00\x00\x00\x00\x02\x32\x30' CmdOnHTTP='' CmdOnPost='' CmdOff='' CmdOffHTTP='' CmdOffPost='' Analog='false' Repeat='0' RepeatRate='0'/>
<VirtualOutCmd Title='LED Helligkeit 21' Comment='' CmdOnMethod='GET' CmdOffMethod='GET' CmdOn='\x00\x00\x02\x01\x2d\x00\x00\x00\x00\x02\x32\x31' CmdOnHTTP='' CmdOnPost='' CmdOff='' CmdOffHTTP='' CmdOffPost='' Analog='false' Repeat='0' RepeatRate='0'/>
<VirtualOutCmd Title='LED Helligkeit 22' Comment='' CmdOnMethod='GET' CmdOffMethod='GET' CmdOn='\x00\x00\x02\x01\x2d\x00\x00\x00\x00\x02\x32\x32' CmdOnHTTP='' CmdOnPost='' CmdOff='' CmdOffHTTP='' CmdOffPost='' Analog='false' Repeat='0' RepeatRate='0'/>
<VirtualOutCmd Title='LED Helligkeit 23' Comment='' CmdOnMethod='GET' CmdOffMethod='GET' CmdOn='\x00\x00\x02\x01\x2d\x00\x00\x00\x00\x02\x32\x33' CmdOnHTTP='' CmdOnPost='' CmdOff='' CmdOffHTTP='' CmdOffPost='' Analog='false' Repeat='0' RepeatRate='0'/>
<VirtualOutCmd Title='LED Helligkeit 24' Comment='' CmdOnMethod='GET' CmdOffMethod='GET' CmdOn='\x00\x00\x02\x01\x2d\x00\x00\x00\x00\x02\x32\x34' CmdOnHTTP='' CmdOnPost='' CmdOff='' CmdOffHTTP='' CmdOffPost='' Analog='false' Repeat='0' RepeatRate='0'/>
<VirtualOutCmd Title='LED Helligkeit 25' Comment='' CmdOnMethod='GET' CmdOffMethod='GET' CmdOn='\x00\x00\x02\x01\x2d\x00\x00\x00\x00\x02\x32\x35' CmdOnHTTP='' CmdOnPost='' CmdOff='' CmdOffHTTP='' CmdOffPost='' Analog='false' Repeat='0' RepeatRate='0'/>
<VirtualOutCmd Title='LED Helligkeit 26' Comment='' CmdOnMethod='GET' CmdOffMethod='GET' CmdOn='\x00\x00\x02\x01\x2d\x00\x00\x00\x00\x02\x32\x36' CmdOnHTTP='' CmdOnPost='' CmdOff='' CmdOffHTTP='' CmdOffPost='' Analog='false' Repeat='0' RepeatRate='0'/>
<VirtualOutCmd Title='LED Helligkeit 27' Comment='' CmdOnMethod='GET' CmdOffMethod='GET' CmdOn='\x00\x00\x02\x01\x2d\x00\x00\x00\x00\x02\x32\x37' CmdOnHTTP='' CmdOnPost='' CmdOff='' CmdOffHTTP='' CmdOffPost='' Analog='false' Repeat='0' RepeatRate='0'/>
<VirtualOutCmd Title='LED Helligkeit 28' Comment='' CmdOnMethod='GET' CmdOffMethod='GET' CmdOn='\x00\x00\x02\x01\x2d\x00\x00\x00\x00\x02\x32\x38' CmdOnHTTP='' CmdOnPost='' CmdOff='' CmdOffHTTP='' CmdOffPost='' Analog='false' Repeat='0' RepeatRate='0'/>
<VirtualOutCmd Title='LED Helligkeit 29' Comment='' CmdOnMethod='GET' CmdOffMethod='GET' CmdOn='\x00\x00\x02\x01\x2d\x00\x00\x00\x00\x02\x32\x39' CmdOnHTTP='' CmdOnPost='' CmdOff='' CmdOffHTTP='' CmdOffPost='' Analog='false' Repeat='0' RepeatRate='0'/>
<VirtualOutCmd Title='LED Helligkeit 30' Comment='' CmdOnMethod='GET' CmdOffMethod='GET' CmdOn='\x00\x00\x02\x01\x2d\x00\x00\x00\x00\x02\x33\x30' CmdOnHTTP='' CmdOnPost='' CmdOff='' CmdOffHTTP='' CmdOffPost='' Analog='false' Repeat='0' RepeatRate='0'/>
<VirtualOutCmd Title='LED Helligkeit 31' Comment='' CmdOnMethod='GET' CmdOffMethod='GET' CmdOn='\x00\x00\x02\x01\x2d\x00\x00\x00\x00\x02\x33\x31' CmdOnHTTP='' CmdOnPost='' CmdOff='' CmdOffHTTP='' CmdOffPost='' Analog='false' Repeat='0' RepeatRate='0'/>
<VirtualOutCmd Title='LED Helligkeit 32' Comment='' CmdOnMethod='GET' CmdOffMethod='GET' CmdOn='\x00\x00\x02\x01\x2d\x00\x00\x00\x00\x02\x33\x32' CmdOnHTTP='' CmdOnPost='' CmdOff='' CmdOffHTTP='' CmdOffPost='' Analog='false' Repeat='0' RepeatRate='0'/>
<VirtualOutCmd Title='LED Helligkeit 33' Comment='' CmdOnMethod='GET' CmdOffMethod='GET' CmdOn='\x00\x00\x02\x01\x2d\x00\x00\x00\x00\x02\x33\x33' CmdOnHTTP='' CmdOnPost='' CmdOff='' CmdOffHTTP='' CmdOffPost='' Analog='false' Repeat='0' RepeatRate='0'/>
<VirtualOutCmd Title='LED Helligkeit 34' Comment='' CmdOnMethod='GET' CmdOffMethod='GET' CmdOn='\x00\x00\x02\x01\x2d\x00\x00\x00\x00\x02\x33\x34' CmdOnHTTP='' CmdOnPost='' CmdOff='' CmdOffHTTP='' CmdOffPost='' Analog='false' Repeat='0' RepeatRate='0'/>
<VirtualOutCmd Title='LED Helligkeit 35' Comment='' CmdOnMethod='GET' CmdOffMethod='GET' CmdOn='\x00\x00\x02\x01\x2d\x00\x00\x00\x00\x02\x33\x35' CmdOnHTTP='' CmdOnPost='' CmdOff='' CmdOffHTTP='' CmdOffPost='' Analog='false' Repeat='0' RepeatRate='0'/>
<VirtualOutCmd Title='LED Helligkeit 36' Comment='' CmdOnMethod='GET' CmdOffMethod='GET' CmdOn='\x00\x00\x02\x01\x2d\x00\x00\x00\x00\x02\x33\x36' CmdOnHTTP='' CmdOnPost='' CmdOff='' CmdOffHTTP='' CmdOffPost='' Analog='false' Repeat='0' RepeatRate='0'/>
<VirtualOutCmd Title='LED Helligkeit 37' Comment='' CmdOnMethod='GET' CmdOffMethod='GET' CmdOn='\x00\x00\x02\x01\x2d\x00\x00\x00\x00\x02\x33\x37' CmdOnHTTP='' CmdOnPost='' CmdOff='' CmdOffHTTP='' CmdOffPost='' Analog='false' Repeat='0' RepeatRate='0'/>
<VirtualOutCmd Title='LED Helligkeit 38' Comment='' CmdOnMethod='GET' CmdOffMethod='GET' CmdOn='\x00\x00\x02\x01\x2d\x00\x00\x00\x00\x02\x33\x38' CmdOnHTTP='' CmdOnPost='' CmdOff='' CmdOffHTTP='' CmdOffPost='' Analog='false' Repeat='0' RepeatRate='0'/>
<VirtualOutCmd Title='LED Helligkeit 39' Comment='' CmdOnMethod='GET' CmdOffMethod='GET' CmdOn='\x00\x00\x02\x01\x2d\x00\x00\x00\x00\x02\x33\x39' CmdOnHTTP='' CmdOnPost='' CmdOff='' CmdOffHTTP='' CmdOffPost='' Analog='false' Repeat='0' RepeatRate='0'/>
<VirtualOutCmd Title='LED Helligkeit 40' Comment='' CmdOnMethod='GET' CmdOffMethod='GET' CmdOn='\x00\x00\x02\x01\x2d\x00\x00\x00\x00\x02\x34\x30' CmdOnHTTP='' CmdOnPost='' CmdOff='' CmdOffHTTP='' CmdOffPost='' Analog='false' Repeat='0' RepeatRate='0'/>
<VirtualOutCmd Title='LED Helligkeit 41' Comment='' CmdOnMethod='GET' CmdOffMethod='GET' CmdOn='\x00\x00\x02\x01\x2d\x00\x00\x00\x00\x02\x34\x31' CmdOnHTTP='' CmdOnPost='' CmdOff='' CmdOffHTTP='' CmdOffPost='' Analog='false' Repeat='0' RepeatRate='0'/>
<VirtualOutCmd Title='LED Helligkeit 42' Comment='' CmdOnMethod='GET' CmdOffMethod='GET' CmdOn='\x00\x00\x02\x01\x2d\x00\x00\x00\x00\x02\x34\x32' CmdOnHTTP='' CmdOnPost='' CmdOff='' CmdOffHTTP='' CmdOffPost='' Analog='false' Repeat='0' RepeatRate='0'/>
<VirtualOutCmd Title='LED Helligkeit 43' Comment='' CmdOnMethod='GET' CmdOffMethod='GET' CmdOn='\x00\x00\x02\x01\x2d\x00\x00\x00\x00\x02\x34\x33' CmdOnHTTP='' CmdOnPost='' CmdOff='' CmdOffHTTP='' CmdOffPost='' Analog='false' Repeat='0' RepeatRate='0'/>
<VirtualOutCmd Title='LED Helligkeit 44' Comment='' CmdOnMethod='GET' CmdOffMethod='GET' CmdOn='\x00\x00\x02\x01\x2d\x00\x00\x00\x00\x02\x34\x34' CmdOnHTTP='' CmdOnPost='' CmdOff='' CmdOffHTTP='' CmdOffPost='' Analog='false' Repeat='0' RepeatRate='0'/>
<VirtualOutCmd Title='LED Helligkeit 45' Comment='' CmdOnMethod='GET' CmdOffMethod='GET' CmdOn='\x00\x00\x02\x01\x2d\x00\x00\x00\x00\x02\x34\x35' CmdOnHTTP='' CmdOnPost='' CmdOff='' CmdOffHTTP='' CmdOffPost='' Analog='false' Repeat='0' RepeatRate='0'/>
<VirtualOutCmd Title='LED Helligkeit 46' Comment='' CmdOnMethod='GET' CmdOffMethod='GET' CmdOn='\x00\x00\x02\x01\x2d\x00\x00\x00\x00\x02\x34\x36' CmdOnHTTP='' CmdOnPost='' CmdOff='' CmdOffHTTP='' CmdOffPost='' Analog='false' Repeat='0' RepeatRate='0'/>
<VirtualOutCmd Title='LED Helligkeit 47' Comment='' CmdOnMethod='GET' CmdOffMethod='GET' CmdOn='\x00\x00\x02\x01\x2d\x00\x00\x00\x00\x02\x34\x37' CmdOnHTTP='' CmdOnPost='' CmdOff='' CmdOffHTTP='' CmdOffPost='' Analog='false' Repeat='0' RepeatRate='0'/>
<VirtualOutCmd Title='LED Helligkeit 48' Comment='' CmdOnMethod='GET' CmdOffMethod='GET' CmdOn='\x00\x00\x02\x01\x2d\x00\x00\x00\x00\x02\x34\x38' CmdOnHTTP='' CmdOnPost='' CmdOff='' CmdOffHTTP='' CmdOffPost='' Analog='false' Repeat='0' RepeatRate='0'/>
<VirtualOutCmd Title='LED Helligkeit 49' Comment='' CmdOnMethod='GET' CmdOffMethod='GET' CmdOn='\x00\x00\x02\x01\x2d\x00\x00\x00\x00\x02\x34\x39' CmdOnHTTP='' CmdOnPost='' CmdOff='' CmdOffHTTP='' CmdOffPost='' Analog='false' Repeat='0' RepeatRate='0'/>
<VirtualOutCmd Title='LED Helligkeit 50' Comment='' CmdOnMethod='GET' CmdOffMethod='GET' CmdOn='\x00\x00\x02\x01\x2d\x00\x00\x00\x00\x02\x35\x30' CmdOnHTTP='' CmdOnPost='' CmdOff='' CmdOffHTTP='' CmdOffPost='' Analog='false' Repeat='0' RepeatRate='0'/>
<VirtualOutCmd Title='LED Helligkeit 51' Comment='' CmdOnMethod='GET' CmdOffMethod='GET' CmdOn='\x00\x00\x02\x01\x2d\x00\x00\x00\x00\x02\x35\x31' CmdOnHTTP='' CmdOnPost='' CmdOff='' CmdOffHTTP='' CmdOffPost='' Analog='false' Repeat='0' RepeatRate='0'/>
<VirtualOutCmd Title='LED Helligkeit 52' Comment='' CmdOnMethod='GET' CmdOffMethod='GET' CmdOn='\x00\x00\x02\x01\x2d\x00\x00\x00\x00\x02\x35\x32' CmdOnHTTP='' CmdOnPost='' CmdOff='' CmdOffHTTP='' CmdOffPost='' Analog='false' Repeat='0' RepeatRate='0'/>
<VirtualOutCmd Title='LED Helligkeit 53' Comment='' CmdOnMethod='GET' CmdOffMethod='GET' CmdOn='\x00\x00\x02\x01\x2d\x00\x00\x00\x00\x02\x35\x33' CmdOnHTTP='' CmdOnPost='' CmdOff='' CmdOffHTTP='' CmdOffPost='' Analog='false' Repeat='0' RepeatRate='0'/>
<VirtualOutCmd Title='LED Helligkeit 54' Comment='' CmdOnMethod='GET' CmdOffMethod='GET' CmdOn='\x00\x00\x02\x01\x2d\x00\x00\x00\x00\x02\x35\x34' CmdOnHTTP='' CmdOnPost='' CmdOff='' CmdOffHTTP='' CmdOffPost='' Analog='false' Repeat='0' RepeatRate='0'/>
<VirtualOutCmd Title='LED Helligkeit 55' Comment='' CmdOnMethod='GET' CmdOffMethod='GET' CmdOn='\x00\x00\x02\x01\x2d\x00\x00\x00\x00\x02\x35\x35' CmdOnHTTP='' CmdOnPost='' CmdOff='' CmdOffHTTP='' CmdOffPost='' Analog='false' Repeat='0' RepeatRate='0'/>
<VirtualOutCmd Title='LED Helligkeit 56' Comment='' CmdOnMethod='GET' CmdOffMethod='GET' CmdOn='\x00\x00\x02\x01\x2d\x00\x00\x00\x00\x02\x35\x36' CmdOnHTTP='' CmdOnPost='' CmdOff='' CmdOffHTTP='' CmdOffPost='' Analog='false' Repeat='0' RepeatRate='0'/>
<VirtualOutCmd Title='LED Helligkeit 57' Comment='' CmdOnMethod='GET' CmdOffMethod='GET' CmdOn='\x00\x00\x02\x01\x2d\x00\x00\x00\x00\x02\x35\x37' CmdOnHTTP='' CmdOnPost='' CmdOff='' CmdOffHTTP='' CmdOffPost='' Analog='false' Repeat='0' RepeatRate='0'/>
<VirtualOutCmd Title='LED Helligkeit 58' Comment='' CmdOnMethod='GET' CmdOffMethod='GET' CmdOn='\x00\x00\x02\x01\x2d\x00\x00\x00\x00\x02\x35\x38' CmdOnHTTP='' CmdOnPost='' CmdOff='' CmdOffHTTP='' CmdOffPost='' Analog='false' Repeat='0' RepeatRate='0'/>
<VirtualOutCmd Title='LED Helligkeit 59' Comment='' CmdOnMethod='GET' CmdOffMethod='GET' CmdOn='\x00\x00\x02\x01\x2d\x00\x00\x00\x00\x02\x35\x39' CmdOnHTTP='' CmdOnPost='' CmdOff='' CmdOffHTTP='' CmdOffPost='' Analog='false' Repeat='0' RepeatRate='0'/>
<VirtualOutCmd Title='LED Helligkeit 60' Comment='' CmdOnMethod='GET' CmdOffMethod='GET' CmdOn='\x00\x00\x02\x01\x2d\x00\x00\x00\x00\x02\x36\x30' CmdOnHTTP='' CmdOnPost='' CmdOff='' CmdOffHTTP='' CmdOffPost='' Analog='false' Repeat='0' RepeatRate='0'/>
<VirtualOutCmd Title='LED Helligkeit 61' Comment='' CmdOnMethod='GET' CmdOffMethod='GET' CmdOn='\x00\x00\x02\x01\x2d\x00\x00\x00\x00\x02\x36\x31' CmdOnHTTP='' CmdOnPost='' CmdOff='' CmdOffHTTP='' CmdOffPost='' Analog='false' Repeat='0' RepeatRate='0'/>
<VirtualOutCmd Title='LED Helligkeit 62' Comment='' CmdOnMethod='GET' CmdOffMethod='GET' CmdOn='\x00\x00\x02\x01\x2d\x00\x00\x00\x00\x02\x36\x32' CmdOnHTTP='' CmdOnPost='' CmdOff='' CmdOffHTTP='' CmdOffPost='' Analog='false' Repeat='0' RepeatRate='0'/>
<VirtualOutCmd Title='LED Helligkeit 63' Comment='' CmdOnMethod='GET' CmdOffMethod='GET' CmdOn='\x00\x00\x02\x01\x2d\x00\x00\x00\x00\x02\x36\x33' CmdOnHTTP='' CmdOnPost='' CmdOff='' CmdOffHTTP='' CmdOffPost='' Analog='false' Repeat='0' RepeatRate='0'/>
<VirtualOutCmd Title='LED Helligkeit 64' Comment='' CmdOnMethod='GET' CmdOffMethod='GET' CmdOn='\x00\x00\x02\x01\x2d\x00\x00\x00\x00\x02\x36\x34' CmdOnHTTP='' CmdOnPost='' CmdOff='' CmdOffHTTP='' CmdOffPost='' Analog='false' Repeat='0' RepeatRate='0'/>
<VirtualOutCmd Title='LED Helligkeit 65' Comment='' CmdOnMethod='GET' CmdOffMethod='GET' CmdOn='\x00\x00\x02\x01\x2d\x00\x00\x00\x00\x02\x36\x35' CmdOnHTTP='' CmdOnPost='' CmdOff='' CmdOffHTTP='' CmdOffPost='' Analog='false' Repeat='0' RepeatRate='0'/>
<VirtualOutCmd Title='LED Helligkeit 66' Comment='' CmdOnMethod='GET' CmdOffMethod='GET' CmdOn='\x00\x00\x02\x01\x2d\x00\x00\x00\x00\x02\x36\x36' CmdOnHTTP='' CmdOnPost='' CmdOff='' CmdOffHTTP='' CmdOffPost='' Analog='false' Repeat='0' RepeatRate='0'/>
<VirtualOutCmd Title='LED Helligkeit 67' Comment='' CmdOnMethod='GET' CmdOffMethod='GET' CmdOn='\x00\x00\x02\x01\x2d\x00\x00\x00\x00\x02\x36\x37' CmdOnHTTP='' CmdOnPost='' CmdOff='' CmdOffHTTP='' CmdOffPost='' Analog='false' Repeat='0' RepeatRate='0'/>
<VirtualOutCmd Title='LED Helligkeit 68' Comment='' CmdOnMethod='GET' CmdOffMethod='GET' CmdOn='\x00\x00\x02\x01\x2d\x00\x00\x00\x00\x02\x36\x38' CmdOnHTTP='' CmdOnPost='' CmdOff='' CmdOffHTTP='' CmdOffPost='' Analog='false' Repeat='0' RepeatRate='0'/>
<VirtualOutCmd Title='LED Helligkeit 69' Comment='' CmdOnMethod='GET' CmdOffMethod='GET' CmdOn='\x00\x00\x02\x01\x2d\x00\x00\x00\x00\x02\x36\x39' CmdOnHTTP='' CmdOnPost='' CmdOff='' CmdOffHTTP='' CmdOffPost='' Analog='false' Repeat='0' RepeatRate='0'/>
<VirtualOutCmd Title='LED Helligkeit 70' Comment='' CmdOnMethod='GET' CmdOffMethod='GET' CmdOn='\x00\x00\x02\x01\x2d\x00\x00\x00\x00\x02\x37\x30' CmdOnHTTP='' CmdOnPost='' CmdOff='' CmdOffHTTP='' CmdOffPost='' Analog='false' Repeat='0' RepeatRate='0'/>
<VirtualOutCmd Title='LED Helligkeit 71' Comment='' CmdOnMethod='GET' CmdOffMethod='GET' CmdOn='\x00\x00\x02\x01\x2d\x00\x00\x00\x00\x02\x37\x31' CmdOnHTTP='' CmdOnPost='' CmdOff='' CmdOffHTTP='' CmdOffPost='' Analog='false' Repeat='0' RepeatRate='0'/>
<VirtualOutCmd Title='LED Helligkeit 72' Comment='' CmdOnMethod='GET' CmdOffMethod='GET' CmdOn='\x00\x00\x02\x01\x2d\x00\x00\x00\x00\x02\x37\x32' CmdOnHTTP='' CmdOnPost='' CmdOff='' CmdOffHTTP='' CmdOffPost='' Analog='false' Repeat='0' RepeatRate='0'/>
<VirtualOutCmd Title='LED Helligkeit 73' Comment='' CmdOnMethod='GET' CmdOffMethod='GET' CmdOn='\x00\x00\x02\x01\x2d\x00\x00\x00\x00\x02\x37\x33' CmdOnHTTP='' CmdOnPost='' CmdOff='' CmdOffHTTP='' CmdOffPost='' Analog='false' Repeat='0' RepeatRate='0'/>
<VirtualOutCmd Title='LED Helligkeit 74' Comment='' CmdOnMethod='GET' CmdOffMethod='GET' CmdOn='\x00\x00\x02\x01\x2d\x00\x00\x00\x00\x02\x37\x34' CmdOnHTTP='' CmdOnPost='' CmdOff='' CmdOffHTTP='' CmdOffPost='' Analog='false' Repeat='0' RepeatRate='0'/>
<VirtualOutCmd Title='LED Helligkeit 75' Comment='' CmdOnMethod='GET' CmdOffMethod='GET' CmdOn='\x00\x00\x02\x01\x2d\x00\x00\x00\x00\x02\x37\x35' CmdOnHTTP='' CmdOnPost='' CmdOff='' CmdOffHTTP='' CmdOffPost='' Analog='false' Repeat='0' RepeatRate='0'/>
<VirtualOutCmd Title='LED Helligkeit 76' Comment='' CmdOnMethod='GET' CmdOffMethod='GET' CmdOn='\x00\x00\x02\x01\x2d\x00\x00\x00\x00\x02\x37\x36' CmdOnHTTP='' CmdOnPost='' CmdOff='' CmdOffHTTP='' CmdOffPost='' Analog='false' Repeat='0' RepeatRate='0'/>
<VirtualOutCmd Title='LED Helligkeit 77' Comment='' CmdOnMethod='GET' CmdOffMethod='GET' CmdOn='\x00\x00\x02\x01\x2d\x00\x00\x00\x00\x02\x37\x37' CmdOnHTTP='' CmdOnPost='' CmdOff='' CmdOffHTTP='' CmdOffPost='' Analog='false' Repeat='0' RepeatRate='0'/>
<VirtualOutCmd Title='LED Helligkeit 78' Comment='' CmdOnMethod='GET' CmdOffMethod='GET' CmdOn='\x00\x00\x02\x01\x2d\x00\x00\x00\x00\x02\x37\x38' CmdOnHTTP='' CmdOnPost='' CmdOff='' CmdOffHTTP='' CmdOffPost='' Analog='false' Repeat='0' RepeatRate='0'/>
<VirtualOutCmd Title='LED Helligkeit 79' Comment='' CmdOnMethod='GET' CmdOffMethod='GET' CmdOn='\x00\x00\x02\x01\x2d\x00\x00\x00\x00\x02\x37\x39' CmdOnHTTP='' CmdOnPost='' CmdOff='' CmdOffHTTP='' CmdOffPost='' Analog='false' Repeat='0' RepeatRate='0'/>
<VirtualOutCmd Title='LED Helligkeit 80' Comment='' CmdOnMethod='GET' CmdOffMethod='GET' CmdOn='\x00\x00\x02\x01\x2d\x00\x00\x00\x00\x02\x38\x30' CmdOnHTTP='' CmdOnPost='' CmdOff='' CmdOffHTTP='' CmdOffPost='' Analog='false' Repeat='0' RepeatRate='0'/>
<VirtualOutCmd Title='LED Helligkeit 81' Comment='' CmdOnMethod='GET' CmdOffMethod='GET' CmdOn='\x00\x00\x02\x01\x2d\x00\x00\x00\x00\x02\x38\x31' CmdOnHTTP='' CmdOnPost='' CmdOff='' CmdOffHTTP='' CmdOffPost='' Analog='false' Repeat='0' RepeatRate='0'/>
<VirtualOutCmd Title='LED Helligkeit 82' Comment='' CmdOnMethod='GET' CmdOffMethod='GET' CmdOn='\x00\x00\x02\x01\x2d\x00\x00\x00\x00\x02\x38\x32' CmdOnHTTP='' CmdOnPost='' CmdOff='' CmdOffHTTP='' CmdOffPost='' Analog='false' Repeat='0' RepeatRate='0'/>
<VirtualOutCmd Title='LED Helligkeit 83' Comment='' CmdOnMethod='GET' CmdOffMethod='GET' CmdOn='\x00\x00\x02\x01\x2d\x00\x00\x00\x00\x02\x38\x33' CmdOnHTTP='' CmdOnPost='' CmdOff='' CmdOffHTTP='' CmdOffPost='' Analog='false' Repeat='0' RepeatRate='0'/>
<VirtualOutCmd Title='LED Helligkeit 84' Comment='' CmdOnMethod='GET' CmdOffMethod='GET' CmdOn='\x00\x00\x02\x01\x2d\x00\x00\x00\x00\x02\x38\x34' CmdOnHTTP='' CmdOnPost='' CmdOff='' CmdOffHTTP='' CmdOffPost='' Analog='false' Repeat='0' RepeatRate='0'/>
<VirtualOutCmd Title='LED Helligkeit 85' Comment='' CmdOnMethod='GET' CmdOffMethod='GET' CmdOn='\x00\x00\x02\x01\x2d\x00\x00\x00\x00\x02\x38\x35' CmdOnHTTP='' CmdOnPost='' CmdOff='' CmdOffHTTP='' CmdOffPost='' Analog='false' Repeat='0' RepeatRate='0'/>
<VirtualOutCmd Title='LED Helligkeit 86' Comment='' CmdOnMethod='GET' CmdOffMethod='GET' CmdOn='\x00\x00\x02\x01\x2d\x00\x00\x00\x00\x02\x38\x36' CmdOnHTTP='' CmdOnPost='' CmdOff='' CmdOffHTTP='' CmdOffPost='' Analog='false' Repeat='0' RepeatRate='0'/>
<VirtualOutCmd Title='LED Helligkeit 87' Comment='' CmdOnMethod='GET' CmdOffMethod='GET' CmdOn='\x00\x00\x02\x01\x2d\x00\x00\x00\x00\x02\x38\x37' CmdOnHTTP='' CmdOnPost='' CmdOff='' CmdOffHTTP='' CmdOffPost='' Analog='false' Repeat='0' RepeatRate='0'/>
<VirtualOutCmd Title='LED Helligkeit 88' Comment='' CmdOnMethod='GET' CmdOffMethod='GET' CmdOn='\x00\x00\x02\x01\x2d\x00\x00\x00\x00\x02\x38\x38' CmdOnHTTP='' CmdOnPost='' CmdOff='' CmdOffHTTP='' CmdOffPost='' Analog='false' Repeat='0' RepeatRate='0'/>
<VirtualOutCmd Title='LED Helligkeit 89' Comment='' CmdOnMethod='GET' CmdOffMethod='GET' CmdOn='\x00\x00\x02\x01\x2d\x00\x00\x00\x00\x02\x38\x39' CmdOnHTTP='' CmdOnPost='' CmdOff='' CmdOffHTTP='' CmdOffPost='' Analog='false' Repeat='0' RepeatRate='0'/>
<VirtualOutCmd Title='LED Helligkeit 90' Comment='' CmdOnMethod='GET' CmdOffMethod='GET' CmdOn='\x00\x00\x02\x01\x2d\x00\x00\x00\x00\x02\x39\x30' CmdOnHTTP='' CmdOnPost='' CmdOff='' CmdOffHTTP='' CmdOffPost='' Analog='false' Repeat='0' RepeatRate='0'/>
<VirtualOutCmd Title='LED Helligkeit 91' Comment='' CmdOnMethod='GET' CmdOffMethod='GET' CmdOn='\x00\x00\x02\x01\x2d\x00\x00\x00\x00\x02\x39\x31' CmdOnHTTP='' CmdOnPost='' CmdOff='' CmdOffHTTP='' CmdOffPost='' Analog='false' Repeat='0' RepeatRate='0'/>
<VirtualOutCmd Title='LED Helligkeit 92' Comment='' CmdOnMethod='GET' CmdOffMethod='GET' CmdOn='\x00\x00\x02\x01\x2d\x00\x00\x00\x00\x02\x39\x32' CmdOnHTTP='' CmdOnPost='' CmdOff='' CmdOffHTTP='' CmdOffPost='' Analog='false' Repeat='0' RepeatRate='0'/>
<VirtualOutCmd Title='LED Helligkeit 93' Comment='' CmdOnMethod='GET' CmdOffMethod='GET' CmdOn='\x00\x00\x02\x01\x2d\x00\x00\x00\x00\x02\x39\x33' CmdOnHTTP='' CmdOnPost='' CmdOff='' CmdOffHTTP='' CmdOffPost='' Analog='false' Repeat='0' RepeatRate='0'/>
<VirtualOutCmd Title='LED Helligkeit 94' Comment='' CmdOnMethod='GET' CmdOffMethod='GET' CmdOn='\x00\x00\x02\x01\x2d\x00\x00\x00\x00\x02\x39\x34' CmdOnHTTP='' CmdOnPost='' CmdOff='' CmdOffHTTP='' CmdOffPost='' Analog='false' Repeat='0' RepeatRate='0'/>
<VirtualOutCmd Title='LED Helligkeit 95' Comment='' CmdOnMethod='GET' CmdOffMethod='GET' CmdOn='\x00\x00\x02\x01\x2d\x00\x00\x00\x00\x02\x39\x35' CmdOnHTTP='' CmdOnPost='' CmdOff='' CmdOffHTTP='' CmdOffPost='' Analog='false' Repeat='0' RepeatRate='0'/>
<VirtualOutCmd Title='LED Helligkeit 96' Comment='' CmdOnMethod='GET' CmdOffMethod='GET' CmdOn='\x00\x00\x02\x01\x2d\x00\x00\x00\x00\x02\x39\x36' CmdOnHTTP='' CmdOnPost='' CmdOff='' CmdOffHTTP='' CmdOffPost='' Analog='false' Repeat='0' RepeatRate='0'/>
<VirtualOutCmd Title='LED Helligkeit 97' Comment='' CmdOnMethod='GET' CmdOffMethod='GET' CmdOn='\x00\x00\x02\x01\x2d\x00\x00\x00\x00\x02\x39\x37' CmdOnHTTP='' CmdOnPost='' CmdOff='' CmdOffHTTP='' CmdOffPost='' Analog='false' Repeat='0' RepeatRate='0'/>
<VirtualOutCmd Title='LED Helligkeit 98' Comment='' CmdOnMethod='GET' CmdOffMethod='GET' CmdOn='\x00\x00\x02\x01\x2d\x00\x00\x00\x00\x02\x39\x38' CmdOnHTTP='' CmdOnPost='' CmdOff='' CmdOffHTTP='' CmdOffPost='' Analog='false' Repeat='0' RepeatRate='0'/>
<VirtualOutCmd Title='LED Helligkeit 99' Comment='' CmdOnMethod='GET' CmdOffMethod='GET' CmdOn='\x00\x00\x02\x01\x2d\x00\x00\x00\x00\x02\x39\x39' CmdOnHTTP='' CmdOnPost='' CmdOff='' CmdOffHTTP='' CmdOffPost='' Analog='false' Repeat='0' RepeatRate='0'/>
<VirtualOutCmd Title='LED Helligkeit 100' Comment='' CmdOnMethod='GET' CmdOffMethod='GET' CmdOn='\x00\x00\x02\x01\x2d\x00\x00\x04\x00\x03\x31\x30\x30' CmdOnHTTP='' CmdOnPost='' CmdOff='' CmdOffHTTP='' CmdOffPost='' Analog='false' Repeat='0' RepeatRate='0'/>
<VirtualOutCmd Title='Volume V einstellig' Comment='' CmdOnMethod='GET' CmdOffMethod='GET' CmdOn='\x00\x00\x02\x00\x40\x00\x00\x00\x00\x02\x30&lt;v&gt;' CmdOnHTTP='' CmdOnPost='' CmdOff='' CmdOffHTTP='' CmdOffPost='' Analog='true' Repeat='0' RepeatRate='0'/>
<VirtualOutCmd Title='Volume V zweistellig' Comment='' CmdOnMethod='GET' CmdOffMethod='GET' CmdOn='\x00\x00\x02\x00\x40\x00\x00\x00\x00\x02&lt;v&gt;' CmdOnHTTP='' CmdOnPost='' CmdOff='' CmdOffHTTP='' CmdOffPost='' Analog='true' Repeat='0' RepeatRate='0'/>
<VirtualOutCmd Title='Volume V dreistellig' Comment='' CmdOnMethod='GET' CmdOffMethod='GET' CmdOn='\x00\x00\x02\x00\x40\x00\x00\x00\x00\x03&lt;v&gt;' CmdOnHTTP='' CmdOnPost='' CmdOff='' CmdOffHTTP='' CmdOffPost='' Analog='true' Repeat='0' RepeatRate='0'/>
<VirtualOutCmd Title='Volume 0' Comment='' CmdOnMethod='GET' CmdOffMethod='GET' CmdOn='\x00\x00\x02\x00\x40\x00\x00\x00\x00\x02\x30\x30' CmdOnHTTP='' CmdOnPost='' CmdOff='' CmdOffHTTP='' CmdOffPost='' Analog='false' Repeat='0' RepeatRate='0'/>
<VirtualOutCmd Title='Volume 1' Comment='' CmdOnMethod='GET' CmdOffMethod='GET' CmdOn='\x00\x00\x02\x00\x40\x00\x00\x00\x00\x02\x30\x31' CmdOnHTTP='' CmdOnPost='' CmdOff='' CmdOffHTTP='' CmdOffPost='' Analog='false' Repeat='0' RepeatRate='0'/>
<VirtualOutCmd Title='Volume 2' Comment='' CmdOnMethod='GET' CmdOffMethod='GET' CmdOn='\x00\x00\x02\x00\x40\x00\x00\x00\x00\x02\x30\x32' CmdOnHTTP='' CmdOnPost='' CmdOff='' CmdOffHTTP='' CmdOffPost='' Analog='false' Repeat='0' RepeatRate='0'/>
<VirtualOutCmd Title='Volume 3' Comment='' CmdOnMethod='GET' CmdOffMethod='GET' CmdOn='\x00\x00\x02\x00\x40\x00\x00\x00\x00\x02\x30\x33' CmdOnHTTP='' CmdOnPost='' CmdOff='' CmdOffHTTP='' CmdOffPost='' Analog='false' Repeat='0' RepeatRate='0'/>
<VirtualOutCmd Title='Volume 4' Comment='' CmdOnMethod='GET' CmdOffMethod='GET' CmdOn='\x00\x00\x02\x00\x40\x00\x00\x00\x00\x02\x30\x34' CmdOnHTTP='' CmdOnPost='' CmdOff='' CmdOffHTTP='' CmdOffPost='' Analog='false' Repeat='0' RepeatRate='0'/>
<VirtualOutCmd Title='Volume 5' Comment='' CmdOnMethod='GET' CmdOffMethod='GET' CmdOn='\x00\x00\x02\x00\x40\x00\x00\x00\x00\x02\x30\x35' CmdOnHTTP='' CmdOnPost='' CmdOff='' CmdOffHTTP='' CmdOffPost='' Analog='false' Repeat='0' RepeatRate='0'/>
<VirtualOutCmd Title='Volume 6' Comment='' CmdOnMethod='GET' CmdOffMethod='GET' CmdOn='\x00\x00\x02\x00\x40\x00\x00\x00\x00\x02\x30\x36' CmdOnHTTP='' CmdOnPost='' CmdOff='' CmdOffHTTP='' CmdOffPost='' Analog='false' Repeat='0' RepeatRate='0'/>
<VirtualOutCmd Title='Volume 7' Comment='' CmdOnMethod='GET' CmdOffMethod='GET' CmdOn='\x00\x00\x02\x00\x40\x00\x00\x00\x00\x02\x30\x37' CmdOnHTTP='' CmdOnPost='' CmdOff='' CmdOffHTTP='' CmdOffPost='' Analog='false' Repeat='0' RepeatRate='0'/>
<VirtualOutCmd Title='Volume 8' Comment='' CmdOnMethod='GET' CmdOffMethod='GET' CmdOn='\x00\x00\x02\x00\x40\x00\x00\x00\x00\x02\x30\x38' CmdOnHTTP='' CmdOnPost='' CmdOff='' CmdOffHTTP='' CmdOffPost='' Analog='false' Repeat='0' RepeatRate='0'/>
<VirtualOutCmd Title='Volume 9' Comment='' CmdOnMethod='GET' CmdOffMethod='GET' CmdOn='\x00\x00\x02\x00\x40\x00\x00\x00\x00\x02\x30\x39' CmdOnHTTP='' CmdOnPost='' CmdOff='' CmdOffHTTP='' CmdOffPost='' Analog='false' Repeat='0' RepeatRate='0'/>
<VirtualOutCmd Title='Volume 10' Comment='' CmdOnMethod='GET' CmdOffMethod='GET' CmdOn='\x00\x00\x02\x00\x40\x00\x00\x00\x00\x02\x31\x30' CmdOnHTTP='' CmdOnPost='' CmdOff='' CmdOffHTTP='' CmdOffPost='' Analog='false' Repeat='0' RepeatRate='0'/>
<VirtualOutCmd Title='Volume 11' Comment='' CmdOnMethod='GET' CmdOffMethod='GET' CmdOn='\x00\x00\x02\x00\x40\x00\x00\x00\x00\x02\x31\x31' CmdOnHTTP='' CmdOnPost='' CmdOff='' CmdOffHTTP='' CmdOffPost='' Analog='false' Repeat='0' RepeatRate='0'/>
<VirtualOutCmd Title='Volume 12' Comment='' CmdOnMethod='GET' CmdOffMethod='GET' CmdOn='\x00\x00\x02\x00\x40\x00\x00\x00\x00\x02\x31\x32' CmdOnHTTP='' CmdOnPost='' CmdOff='' CmdOffHTTP='' CmdOffPost='' Analog='false' Repeat='0' RepeatRate='0'/>
<VirtualOutCmd Title='Volume 13' Comment='' CmdOnMethod='GET' CmdOffMethod='GET' CmdOn='\x00\x00\x02\x00\x40\x00\x00\x00\x00\x02\x31\x33' CmdOnHTTP='' CmdOnPost='' CmdOff='' CmdOffHTTP='' CmdOffPost='' Analog='false' Repeat='0' RepeatRate='0'/>
<VirtualOutCmd Title='Volume 14' Comment='' CmdOnMethod='GET' CmdOffMethod='GET' CmdOn='\x00\x00\x02\x00\x40\x00\x00\x00\x00\x02\x31\x34' CmdOnHTTP='' CmdOnPost='' CmdOff='' CmdOffHTTP='' CmdOffPost='' Analog='false' Repeat='0' RepeatRate='0'/>
<VirtualOutCmd Title='Volume 15' Comment='' CmdOnMethod='GET' CmdOffMethod='GET' CmdOn='\x00\x00\x02\x00\x40\x00\x00\x00\x00\x02\x31\x35' CmdOnHTTP='' CmdOnPost='' CmdOff='' CmdOffHTTP='' CmdOffPost='' Analog='false' Repeat='0' RepeatRate='0'/>
<VirtualOutCmd Title='Volume 16' Comment='' CmdOnMethod='GET' CmdOffMethod='GET' CmdOn='\x00\x00\x02\x00\x40\x00\x00\x00\x00\x02\x31\x36' CmdOnHTTP='' CmdOnPost='' CmdOff='' CmdOffHTTP='' CmdOffPost='' Analog='false' Repeat='0' RepeatRate='0'/>
<VirtualOutCmd Title='Volume 17' Comment='' CmdOnMethod='GET' CmdOffMethod='GET' CmdOn='\x00\x00\x02\x00\x40\x00\x00\x00\x00\x02\x31\x37' CmdOnHTTP='' CmdOnPost='' CmdOff='' CmdOffHTTP='' CmdOffPost='' Analog='false' Repeat='0' RepeatRate='0'/>
<VirtualOutCmd Title='Volume 18' Comment='' CmdOnMethod='GET' CmdOffMethod='GET' CmdOn='\x00\x00\x02\x00\x40\x00\x00\x00\x00\x02\x31\x38' CmdOnHTTP='' CmdOnPost='' CmdOff='' CmdOffHTTP='' CmdOffPost='' Analog='false' Repeat='0' RepeatRate='0'/>
<VirtualOutCmd Title='Volume 19' Comment='' CmdOnMethod='GET' CmdOffMethod='GET' CmdOn='\x00\x00\x02\x00\x40\x00\x00\x00\x00\x02\x31\x39' CmdOnHTTP='' CmdOnPost='' CmdOff='' CmdOffHTTP='' CmdOffPost='' Analog='false' Repeat='0' RepeatRate='0'/>
<VirtualOutCmd Title='Volume 20' Comment='' CmdOnMethod='GET' CmdOffMethod='GET' CmdOn='\x00\x00\x02\x00\x40\x00\x00\x00\x00\x02\x32\x30' CmdOnHTTP='' CmdOnPost='' CmdOff='' CmdOffHTTP='' CmdOffPost='' Analog='false' Repeat='0' RepeatRate='0'/>
<VirtualOutCmd Title='Volume 21' Comment='' CmdOnMethod='GET' CmdOffMethod='GET' CmdOn='\x00\x00\x02\x00\x40\x00\x00\x00\x00\x02\x32\x31' CmdOnHTTP='' CmdOnPost='' CmdOff='' CmdOffHTTP='' CmdOffPost='' Analog='false' Repeat='0' RepeatRate='0'/>
<VirtualOutCmd Title='Volume 22' Comment='' CmdOnMethod='GET' CmdOffMethod='GET' CmdOn='\x00\x00\x02\x00\x40\x00\x00\x00\x00\x02\x32\x32' CmdOnHTTP='' CmdOnPost='' CmdOff='' CmdOffHTTP='' CmdOffPost='' Analog='false' Repeat='0' RepeatRate='0'/>
<VirtualOutCmd Title='Volume 23' Comment='' CmdOnMethod='GET' CmdOffMethod='GET' CmdOn='\x00\x00\x02\x00\x40\x00\x00\x00\x00\x02\x32\x33' CmdOnHTTP='' CmdOnPost='' CmdOff='' CmdOffHTTP='' CmdOffPost='' Analog='false' Repeat='0' RepeatRate='0'/>
<VirtualOutCmd Title='Volume 24' Comment='' CmdOnMethod='GET' CmdOffMethod='GET' CmdOn='\x00\x00\x02\x00\x40\x00\x00\x00\x00\x02\x32\x34' CmdOnHTTP='' CmdOnPost='' CmdOff='' CmdOffHTTP='' CmdOffPost='' Analog='false' Repeat='0' RepeatRate='0'/>
<VirtualOutCmd Title='Volume 25' Comment='' CmdOnMethod='GET' CmdOffMethod='GET' CmdOn='\x00\x00\x02\x00\x40\x00\x00\x00\x00\x02\x32\x35' CmdOnHTTP='' CmdOnPost='' CmdOff='' CmdOffHTTP='' CmdOffPost='' Analog='false' Repeat='0' RepeatRate='0'/>
<VirtualOutCmd Title='Volume 26' Comment='' CmdOnMethod='GET' CmdOffMethod='GET' CmdOn='\x00\x00\x02\x00\x40\x00\x00\x00\x00\x02\x32\x36' CmdOnHTTP='' CmdOnPost='' CmdOff='' CmdOffHTTP='' CmdOffPost='' Analog='false' Repeat='0' RepeatRate='0'/>
<VirtualOutCmd Title='Volume 27' Comment='' CmdOnMethod='GET' CmdOffMethod='GET' CmdOn='\x00\x00\x02\x00\x40\x00\x00\x00\x00\x02\x32\x37' CmdOnHTTP='' CmdOnPost='' CmdOff='' CmdOffHTTP='' CmdOffPost='' Analog='false' Repeat='0' RepeatRate='0'/>
<VirtualOutCmd Title='Volume 28' Comment='' CmdOnMethod='GET' CmdOffMethod='GET' CmdOn='\x00\x00\x02\x00\x40\x00\x00\x00\x00\x02\x32\x38' CmdOnHTTP='' CmdOnPost='' CmdOff='' CmdOffHTTP='' CmdOffPost='' Analog='false' Repeat='0' RepeatRate='0'/>
<VirtualOutCmd Title='Volume 29' Comment='' CmdOnMethod='GET' CmdOffMethod='GET' CmdOn='\x00\x00\x02\x00\x40\x00\x00\x00\x00\x02\x32\x39' CmdOnHTTP='' CmdOnPost='' CmdOff='' CmdOffHTTP='' CmdOffPost='' Analog='false' Repeat='0' RepeatRate='0'/>
<VirtualOutCmd Title='Volume 30' Comment='' CmdOnMethod='GET' CmdOffMethod='GET' CmdOn='\x00\x00\x02\x00\x40\x00\x00\x00\x00\x02\x33\x30' CmdOnHTTP='' CmdOnPost='' CmdOff='' CmdOffHTTP='' CmdOffPost='' Analog='false' Repeat='0' RepeatRate='0'/>
<VirtualOutCmd Title='Volume 31' Comment='' CmdOnMethod='GET' CmdOffMethod='GET' CmdOn='\x00\x00\x02\x00\x40\x00\x00\x00\x00\x02\x33\x31' CmdOnHTTP='' CmdOnPost='' CmdOff='' CmdOffHTTP='' CmdOffPost='' Analog='false' Repeat='0' RepeatRate='0'/>
<VirtualOutCmd Title='Volume 32' Comment='' CmdOnMethod='GET' CmdOffMethod='GET' CmdOn='\x00\x00\x02\x00\x40\x00\x00\x00\x00\x02\x33\x32' CmdOnHTTP='' CmdOnPost='' CmdOff='' CmdOffHTTP='' CmdOffPost='' Analog='false' Repeat='0' RepeatRate='0'/>
<VirtualOutCmd Title='Volume 33' Comment='' CmdOnMethod='GET' CmdOffMethod='GET' CmdOn='\x00\x00\x02\x00\x40\x00\x00\x00\x00\x02\x33\x33' CmdOnHTTP='' CmdOnPost='' CmdOff='' CmdOffHTTP='' CmdOffPost='' Analog='false' Repeat='0' RepeatRate='0'/>
<VirtualOutCmd Title='Volume 34' Comment='' CmdOnMethod='GET' CmdOffMethod='GET' CmdOn='\x00\x00\x02\x00\x40\x00\x00\x00\x00\x02\x33\x34' CmdOnHTTP='' CmdOnPost='' CmdOff='' CmdOffHTTP='' CmdOffPost='' Analog='false' Repeat='0' RepeatRate='0'/>
<VirtualOutCmd Title='Volume 35' Comment='' CmdOnMethod='GET' CmdOffMethod='GET' CmdOn='\x00\x00\x02\x00\x40\x00\x00\x00\x00\x02\x33\x35' CmdOnHTTP='' CmdOnPost='' CmdOff='' CmdOffHTTP='' CmdOffPost='' Analog='false' Repeat='0' RepeatRate='0'/>
<VirtualOutCmd Title='Volume 36' Comment='' CmdOnMethod='GET' CmdOffMethod='GET' CmdOn='\x00\x00\x02\x00\x40\x00\x00\x00\x00\x02\x33\x36' CmdOnHTTP='' CmdOnPost='' CmdOff='' CmdOffHTTP='' CmdOffPost='' Analog='false' Repeat='0' RepeatRate='0'/>
<VirtualOutCmd Title='Volume 37' Comment='' CmdOnMethod='GET' CmdOffMethod='GET' CmdOn='\x00\x00\x02\x00\x40\x00\x00\x00\x00\x02\x33\x37' CmdOnHTTP='' CmdOnPost='' CmdOff='' CmdOffHTTP='' CmdOffPost='' Analog='false' Repeat='0' RepeatRate='0'/>
<VirtualOutCmd Title='Volume 38' Comment='' CmdOnMethod='GET' CmdOffMethod='GET' CmdOn='\x00\x00\x02\x00\x40\x00\x00\x00\x00\x02\x33\x38' CmdOnHTTP='' CmdOnPost='' CmdOff='' CmdOffHTTP='' CmdOffPost='' Analog='false' Repeat='0' RepeatRate='0'/>
<VirtualOutCmd Title='Volume 39' Comment='' CmdOnMethod='GET' CmdOffMethod='GET' CmdOn='\x00\x00\x02\x00\x40\x00\x00\x00\x00\x02\x33\x39' CmdOnHTTP='' CmdOnPost='' CmdOff='' CmdOffHTTP='' CmdOffPost='' Analog='false' Repeat='0' RepeatRate='0'/>
<VirtualOutCmd Title='Volume 40' Comment='' CmdOnMethod='GET' CmdOffMethod='GET' CmdOn='\x00\x00\x02\x00\x40\x00\x00\x00\x00\x02\x34\x30' CmdOnHTTP='' CmdOnPost='' CmdOff='' CmdOffHTTP='' CmdOffPost='' Analog='false' Repeat='0' RepeatRate='0'/>
<VirtualOutCmd Title='Volume 41' Comment='' CmdOnMethod='GET' CmdOffMethod='GET' CmdOn='\x00\x00\x02\x00\x40\x00\x00\x00\x00\x02\x34\x31' CmdOnHTTP='' CmdOnPost='' CmdOff='' CmdOffHTTP='' CmdOffPost='' Analog='false' Repeat='0' RepeatRate='0'/>
<VirtualOutCmd Title='Volume 42' Comment='' CmdOnMethod='GET' CmdOffMethod='GET' CmdOn='\x00\x00\x02\x00\x40\x00\x00\x00\x00\x02\x34\x32' CmdOnHTTP='' CmdOnPost='' CmdOff='' CmdOffHTTP='' CmdOffPost='' Analog='false' Repeat='0' RepeatRate='0'/>
<VirtualOutCmd Title='Volume 43' Comment='' CmdOnMethod='GET' CmdOffMethod='GET' CmdOn='\x00\x00\x02\x00\x40\x00\x00\x00\x00\x02\x34\x33' CmdOnHTTP='' CmdOnPost='' CmdOff='' CmdOffHTTP='' CmdOffPost='' Analog='false' Repeat='0' RepeatRate='0'/>
<VirtualOutCmd Title='Volume 44' Comment='' CmdOnMethod='GET' CmdOffMethod='GET' CmdOn='\x00\x00\x02\x00\x40\x00\x00\x00\x00\x02\x34\x34' CmdOnHTTP='' CmdOnPost='' CmdOff='' CmdOffHTTP='' CmdOffPost='' Analog='false' Repeat='0' RepeatRate='0'/>
<VirtualOutCmd Title='Volume 45' Comment='' CmdOnMethod='GET' CmdOffMethod='GET' CmdOn='\x00\x00\x02\x00\x40\x00\x00\x00\x00\x02\x34\x35' CmdOnHTTP='' CmdOnPost='' CmdOff='' CmdOffHTTP='' CmdOffPost='' Analog='false' Repeat='0' RepeatRate='0'/>
<VirtualOutCmd Title='Volume 46' Comment='' CmdOnMethod='GET' CmdOffMethod='GET' CmdOn='\x00\x00\x02\x00\x40\x00\x00\x00\x00\x02\x34\x36' CmdOnHTTP='' CmdOnPost='' CmdOff='' CmdOffHTTP='' CmdOffPost='' Analog='false' Repeat='0' RepeatRate='0'/>
<VirtualOutCmd Title='Volume 47' Comment='' CmdOnMethod='GET' CmdOffMethod='GET' CmdOn='\x00\x00\x02\x00\x40\x00\x00\x00\x00\x02\x34\x37' CmdOnHTTP='' CmdOnPost='' CmdOff='' CmdOffHTTP='' CmdOffPost='' Analog='false' Repeat='0' RepeatRate='0'/>
<VirtualOutCmd Title='Volume 48' Comment='' CmdOnMethod='GET' CmdOffMethod='GET' CmdOn='\x00\x00\x02\x00\x40\x00\x00\x00\x00\x02\x34\x38' CmdOnHTTP='' CmdOnPost='' CmdOff='' CmdOffHTTP='' CmdOffPost='' Analog='false' Repeat='0' RepeatRate='0'/>
<VirtualOutCmd Title='Volume 49' Comment='' CmdOnMethod='GET' CmdOffMethod='GET' CmdOn='\x00\x00\x02\x00\x40\x00\x00\x00\x00\x02\x34\x39' CmdOnHTTP='' CmdOnPost='' CmdOff='' CmdOffHTTP='' CmdOffPost='' Analog='false' Repeat='0' RepeatRate='0'/>
<VirtualOutCmd Title='Volume 50' Comment='' CmdOnMethod='GET' CmdOffMethod='GET' CmdOn='\x00\x00\x02\x00\x40\x00\x00\x00\x00\x02\x35\x30' CmdOnHTTP='' CmdOnPost='' CmdOff='' CmdOffHTTP='' CmdOffPost='' Analog='false' Repeat='0' RepeatRate='0'/>
<VirtualOutCmd Title='Volume 51' Comment='' CmdOnMethod='GET' CmdOffMethod='GET' CmdOn='\x00\x00\x02\x00\x40\x00\x00\x00\x00\x02\x35\x31' CmdOnHTTP='' CmdOnPost='' CmdOff='' CmdOffHTTP='' CmdOffPost='' Analog='false' Repeat='0' RepeatRate='0'/>
<VirtualOutCmd Title='Volume 52' Comment='' CmdOnMethod='GET' CmdOffMethod='GET' CmdOn='\x00\x00\x02\x00\x40\x00\x00\x00\x00\x02\x35\x32' CmdOnHTTP='' CmdOnPost='' CmdOff='' CmdOffHTTP='' CmdOffPost='' Analog='false' Repeat='0' RepeatRate='0'/>
<VirtualOutCmd Title='Volume 53' Comment='' CmdOnMethod='GET' CmdOffMethod='GET' CmdOn='\x00\x00\x02\x00\x40\x00\x00\x00\x00\x02\x35\x33' CmdOnHTTP='' CmdOnPost='' CmdOff='' CmdOffHTTP='' CmdOffPost='' Analog='false' Repeat='0' RepeatRate='0'/>
<VirtualOutCmd Title='Volume 54' Comment='' CmdOnMethod='GET' CmdOffMethod='GET' CmdOn='\x00\x00\x02\x00\x40\x00\x00\x00\x00\x02\x35\x34' CmdOnHTTP='' CmdOnPost='' CmdOff='' CmdOffHTTP='' CmdOffPost='' Analog='false' Repeat='0' RepeatRate='0'/>
<VirtualOutCmd Title='Volume 55' Comment='' CmdOnMethod='GET' CmdOffMethod='GET' CmdOn='\x00\x00\x02\x00\x40\x00\x00\x00\x00\x02\x35\x35' CmdOnHTTP='' CmdOnPost='' CmdOff='' CmdOffHTTP='' CmdOffPost='' Analog='false' Repeat='0' RepeatRate='0'/>
<VirtualOutCmd Title='Volume 56' Comment='' CmdOnMethod='GET' CmdOffMethod='GET' CmdOn='\x00\x00\x02\x00\x40\x00\x00\x00\x00\x02\x35\x36' CmdOnHTTP='' CmdOnPost='' CmdOff='' CmdOffHTTP='' CmdOffPost='' Analog='false' Repeat='0' RepeatRate='0'/>
<VirtualOutCmd Title='Volume 57' Comment='' CmdOnMethod='GET' CmdOffMethod='GET' CmdOn='\x00\x00\x02\x00\x40\x00\x00\x00\x00\x02\x35\x37' CmdOnHTTP='' CmdOnPost='' CmdOff='' CmdOffHTTP='' CmdOffPost='' Analog='false' Repeat='0' RepeatRate='0'/>
<VirtualOutCmd Title='Volume 58' Comment='' CmdOnMethod='GET' CmdOffMethod='GET' CmdOn='\x00\x00\x02\x00\x40\x00\x00\x00\x00\x02\x35\x38' CmdOnHTTP='' CmdOnPost='' CmdOff='' CmdOffHTTP='' CmdOffPost='' Analog='false' Repeat='0' RepeatRate='0'/>
<VirtualOutCmd Title='Volume 59' Comment='' CmdOnMethod='GET' CmdOffMethod='GET' CmdOn='\x00\x00\x02\x00\x40\x00\x00\x00\x00\x02\x35\x39' CmdOnHTTP='' CmdOnPost='' CmdOff='' CmdOffHTTP='' CmdOffPost='' Analog='false' Repeat='0' RepeatRate='0'/>
<VirtualOutCmd Title='Volume 60' Comment='' CmdOnMethod='GET' CmdOffMethod='GET' CmdOn='\x00\x00\x02\x00\x40\x00\x00\x00\x00\x02\x36\x30' CmdOnHTTP='' CmdOnPost='' CmdOff='' CmdOffHTTP='' CmdOffPost='' Analog='false' Repeat='0' RepeatRate='0'/>
<VirtualOutCmd Title='Volume 61' Comment='' CmdOnMethod='GET' CmdOffMethod='GET' CmdOn='\x00\x00\x02\x00\x40\x00\x00\x00\x00\x02\x36\x31' CmdOnHTTP='' CmdOnPost='' CmdOff='' CmdOffHTTP='' CmdOffPost='' Analog='false' Repeat='0' RepeatRate='0'/>
<VirtualOutCmd Title='Volume 62' Comment='' CmdOnMethod='GET' CmdOffMethod='GET' CmdOn='\x00\x00\x02\x00\x40\x00\x00\x00\x00\x02\x36\x32' CmdOnHTTP='' CmdOnPost='' CmdOff='' CmdOffHTTP='' CmdOffPost='' Analog='false' Repeat='0' RepeatRate='0'/>
<VirtualOutCmd Title='Volume 63' Comment='' CmdOnMethod='GET' CmdOffMethod='GET' CmdOn='\x00\x00\x02\x00\x40\x00\x00\x00\x00\x02\x36\x33' CmdOnHTTP='' CmdOnPost='' CmdOff='' CmdOffHTTP='' CmdOffPost='' Analog='false' Repeat='0' RepeatRate='0'/>
<VirtualOutCmd Title='Volume 64' Comment='' CmdOnMethod='GET' CmdOffMethod='GET' CmdOn='\x00\x00\x02\x00\x40\x00\x00\x00\x00\x02\x36\x34' CmdOnHTTP='' CmdOnPost='' CmdOff='' CmdOffHTTP='' CmdOffPost='' Analog='false' Repeat='0' RepeatRate='0'/>
<VirtualOutCmd Title='Volume 65' Comment='' CmdOnMethod='GET' CmdOffMethod='GET' CmdOn='\x00\x00\x02\x00\x40\x00\x00\x00\x00\x02\x36\x35' CmdOnHTTP='' CmdOnPost='' CmdOff='' CmdOffHTTP='' CmdOffPost='' Analog='false' Repeat='0' RepeatRate='0'/>
<VirtualOutCmd Title='Volume 66' Comment='' CmdOnMethod='GET' CmdOffMethod='GET' CmdOn='\x00\x00\x02\x00\x40\x00\x00\x00\x00\x02\x36\x36' CmdOnHTTP='' CmdOnPost='' CmdOff='' CmdOffHTTP='' CmdOffPost='' Analog='false' Repeat='0' RepeatRate='0'/>
<VirtualOutCmd Title='Volume 67' Comment='' CmdOnMethod='GET' CmdOffMethod='GET' CmdOn='\x00\x00\x02\x00\x40\x00\x00\x00\x00\x02\x36\x37' CmdOnHTTP='' CmdOnPost='' CmdOff='' CmdOffHTTP='' CmdOffPost='' Analog='false' Repeat='0' RepeatRate='0'/>
<VirtualOutCmd Title='Volume 68' Comment='' CmdOnMethod='GET' CmdOffMethod='GET' CmdOn='\x00\x00\x02\x00\x40\x00\x00\x00\x00\x02\x36\x38' CmdOnHTTP='' CmdOnPost='' CmdOff='' CmdOffHTTP='' CmdOffPost='' Analog='false' Repeat='0' RepeatRate='0'/>
<VirtualOutCmd Title='Volume 69' Comment='' CmdOnMethod='GET' CmdOffMethod='GET' CmdOn='\x00\x00\x02\x00\x40\x00\x00\x00\x00\x02\x36\x39' CmdOnHTTP='' CmdOnPost='' CmdOff='' CmdOffHTTP='' CmdOffPost='' Analog='false' Repeat='0' RepeatRate='0'/>
<VirtualOutCmd Title='Volume 70' Comment='' CmdOnMethod='GET' CmdOffMethod='GET' CmdOn='\x00\x00\x02\x00\x40\x00\x00\x00\x00\x02\x37\x30' CmdOnHTTP='' CmdOnPost='' CmdOff='' CmdOffHTTP='' CmdOffPost='' Analog='false' Repeat='0' RepeatRate='0'/>
<VirtualOutCmd Title='Volume 71' Comment='' CmdOnMethod='GET' CmdOffMethod='GET' CmdOn='\x00\x00\x02\x00\x40\x00\x00\x00\x00\x02\x37\x31' CmdOnHTTP='' CmdOnPost='' CmdOff='' CmdOffHTTP='' CmdOffPost='' Analog='false' Repeat='0' RepeatRate='0'/>
<VirtualOutCmd Title='Volume 72' Comment='' CmdOnMethod='GET' CmdOffMethod='GET' CmdOn='\x00\x00\x02\x00\x40\x00\x00\x00\x00\x02\x37\x32' CmdOnHTTP='' CmdOnPost='' CmdOff='' CmdOffHTTP='' CmdOffPost='' Analog='false' Repeat='0' RepeatRate='0'/>
<VirtualOutCmd Title='Volume 73' Comment='' CmdOnMethod='GET' CmdOffMethod='GET' CmdOn='\x00\x00\x02\x00\x40\x00\x00\x00\x00\x02\x37\x33' CmdOnHTTP='' CmdOnPost='' CmdOff='' CmdOffHTTP='' CmdOffPost='' Analog='false' Repeat='0' RepeatRate='0'/>
<VirtualOutCmd Title='Volume 74' Comment='' CmdOnMethod='GET' CmdOffMethod='GET' CmdOn='\x00\x00\x02\x00\x40\x00\x00\x00\x00\x02\x37\x34' CmdOnHTTP='' CmdOnPost='' CmdOff='' CmdOffHTTP='' CmdOffPost='' Analog='false' Repeat='0' RepeatRate='0'/>
<VirtualOutCmd Title='Volume 75' Comment='' CmdOnMethod='GET' CmdOffMethod='GET' CmdOn='\x00\x00\x02\x00\x40\x00\x00\x00\x00\x02\x37\x35' CmdOnHTTP='' CmdOnPost='' CmdOff='' CmdOffHTTP='' CmdOffPost='' Analog='false' Repeat='0' RepeatRate='0'/>
<VirtualOutCmd Title='Volume 76' Comment='' CmdOnMethod='GET' CmdOffMethod='GET' CmdOn='\x00\x00\x02\x00\x40\x00\x00\x00\x00\x02\x37\x36' CmdOnHTTP='' CmdOnPost='' CmdOff='' CmdOffHTTP='' CmdOffPost='' Analog='false' Repeat='0' RepeatRate='0'/>
<VirtualOutCmd Title='Volume 77' Comment='' CmdOnMethod='GET' CmdOffMethod='GET' CmdOn='\x00\x00\x02\x00\x40\x00\x00\x00\x00\x02\x37\x37' CmdOnHTTP='' CmdOnPost='' CmdOff='' CmdOffHTTP='' CmdOffPost='' Analog='false' Repeat='0' RepeatRate='0'/>
<VirtualOutCmd Title='Volume 78' Comment='' CmdOnMethod='GET' CmdOffMethod='GET' CmdOn='\x00\x00\x02\x00\x40\x00\x00\x00\x00\x02\x37\x38' CmdOnHTTP='' CmdOnPost='' CmdOff='' CmdOffHTTP='' CmdOffPost='' Analog='false' Repeat='0' RepeatRate='0'/>
<VirtualOutCmd Title='Volume 79' Comment='' CmdOnMethod='GET' CmdOffMethod='GET' CmdOn='\x00\x00\x02\x00\x40\x00\x00\x00\x00\x02\x37\x39' CmdOnHTTP='' CmdOnPost='' CmdOff='' CmdOffHTTP='' CmdOffPost='' Analog='false' Repeat='0' RepeatRate='0'/>
<VirtualOutCmd Title='Volume 80' Comment='' CmdOnMethod='GET' CmdOffMethod='GET' CmdOn='\x00\x00\x02\x00\x40\x00\x00\x00\x00\x02\x38\x30' CmdOnHTTP='' CmdOnPost='' CmdOff='' CmdOffHTTP='' CmdOffPost='' Analog='false' Repeat='0' RepeatRate='0'/>
<VirtualOutCmd Title='Volume 81' Comment='' CmdOnMethod='GET' CmdOffMethod='GET' CmdOn='\x00\x00\x02\x00\x40\x00\x00\x00\x00\x02\x38\x31' CmdOnHTTP='' CmdOnPost='' CmdOff='' CmdOffHTTP='' CmdOffPost='' Analog='false' Repeat='0' RepeatRate='0'/>
<VirtualOutCmd Title='Volume 82' Comment='' CmdOnMethod='GET' CmdOffMethod='GET' CmdOn='\x00\x00\x02\x00\x40\x00\x00\x00\x00\x02\x38\x32' CmdOnHTTP='' CmdOnPost='' CmdOff='' CmdOffHTTP='' CmdOffPost='' Analog='false' Repeat='0' RepeatRate='0'/>
<VirtualOutCmd Title='Volume 83' Comment='' CmdOnMethod='GET' CmdOffMethod='GET' CmdOn='\x00\x00\x02\x00\x40\x00\x00\x00\x00\x02\x38\x33' CmdOnHTTP='' CmdOnPost='' CmdOff='' CmdOffHTTP='' CmdOffPost='' Analog='false' Repeat='0' RepeatRate='0'/>
<VirtualOutCmd Title='Volume 84' Comment='' CmdOnMethod='GET' CmdOffMethod='GET' CmdOn='\x00\x00\x02\x00\x40\x00\x00\x00\x00\x02\x38\x34' CmdOnHTTP='' CmdOnPost='' CmdOff='' CmdOffHTTP='' CmdOffPost='' Analog='false' Repeat='0' RepeatRate='0'/>
<VirtualOutCmd Title='Volume 85' Comment='' CmdOnMethod='GET' CmdOffMethod='GET' CmdOn='\x00\x00\x02\x00\x40\x00\x00\x00\x00\x02\x38\x35' CmdOnHTTP='' CmdOnPost='' CmdOff='' CmdOffHTTP='' CmdOffPost='' Analog='false' Repeat='0' RepeatRate='0'/>
<VirtualOutCmd Title='Volume 86' Comment='' CmdOnMethod='GET' CmdOffMethod='GET' CmdOn='\x00\x00\x02\x00\x40\x00\x00\x00\x00\x02\x38\x36' CmdOnHTTP='' CmdOnPost='' CmdOff='' CmdOffHTTP='' CmdOffPost='' Analog='false' Repeat='0' RepeatRate='0'/>
<VirtualOutCmd Title='Volume 87' Comment='' CmdOnMethod='GET' CmdOffMethod='GET' CmdOn='\x00\x00\x02\x00\x40\x00\x00\x00\x00\x02\x38\x37' CmdOnHTTP='' CmdOnPost='' CmdOff='' CmdOffHTTP='' CmdOffPost='' Analog='false' Repeat='0' RepeatRate='0'/>
<VirtualOutCmd Title='Volume 88' Comment='' CmdOnMethod='GET' CmdOffMethod='GET' CmdOn='\x00\x00\x02\x00\x40\x00\x00\x00\x00\x02\x38\x38' CmdOnHTTP='' CmdOnPost='' CmdOff='' CmdOffHTTP='' CmdOffPost='' Analog='false' Repeat='0' RepeatRate='0'/>
<VirtualOutCmd Title='Volume 89' Comment='' CmdOnMethod='GET' CmdOffMethod='GET' CmdOn='\x00\x00\x02\x00\x40\x00\x00\x00\x00\x02\x38\x39' CmdOnHTTP='' CmdOnPost='' CmdOff='' CmdOffHTTP='' CmdOffPost='' Analog='false' Repeat='0' RepeatRate='0'/>
<VirtualOutCmd Title='Volume 90' Comment='' CmdOnMethod='GET' CmdOffMethod='GET' CmdOn='\x00\x00\x02\x00\x40\x00\x00\x00\x00\x02\x39\x30' CmdOnHTTP='' CmdOnPost='' CmdOff='' CmdOffHTTP='' CmdOffPost='' Analog='false' Repeat='0' RepeatRate='0'/>
<VirtualOutCmd Title='Volume 91' Comment='' CmdOnMethod='GET' CmdOffMethod='GET' CmdOn='\x00\x00\x02\x00\x40\x00\x00\x00\x00\x02\x39\x31' CmdOnHTTP='' CmdOnPost='' CmdOff='' CmdOffHTTP='' CmdOffPost='' Analog='false' Repeat='0' RepeatRate='0'/>
<VirtualOutCmd Title='Volume 92' Comment='' CmdOnMethod='GET' CmdOffMethod='GET' CmdOn='\x00\x00\x02\x00\x40\x00\x00\x00\x00\x02\x39\x32' CmdOnHTTP='' CmdOnPost='' CmdOff='' CmdOffHTTP='' CmdOffPost='' Analog='false' Repeat='0' RepeatRate='0'/>
<VirtualOutCmd Title='Volume 93' Comment='' CmdOnMethod='GET' CmdOffMethod='GET' CmdOn='\x00\x00\x02\x00\x40\x00\x00\x00\x00\x02\x39\x33' CmdOnHTTP='' CmdOnPost='' CmdOff='' CmdOffHTTP='' CmdOffPost='' Analog='false' Repeat='0' RepeatRate='0'/>
<VirtualOutCmd Title='Volume 94' Comment='' CmdOnMethod='GET' CmdOffMethod='GET' CmdOn='\x00\x00\x02\x00\x40\x00\x00\x00\x00\x02\x39\x34' CmdOnHTTP='' CmdOnPost='' CmdOff='' CmdOffHTTP='' CmdOffPost='' Analog='false' Repeat='0' RepeatRate='0'/>
<VirtualOutCmd Title='Volume 95' Comment='' CmdOnMethod='GET' CmdOffMethod='GET' CmdOn='\x00\x00\x02\x00\x40\x00\x00\x00\x00\x02\x39\x35' CmdOnHTTP='' CmdOnPost='' CmdOff='' CmdOffHTTP='' CmdOffPost='' Analog='false' Repeat='0' RepeatRate='0'/>
<VirtualOutCmd Title='Volume 96' Comment='' CmdOnMethod='GET' CmdOffMethod='GET' CmdOn='\x00\x00\x02\x00\x40\x00\x00\x00\x00\x02\x39\x36' CmdOnHTTP='' CmdOnPost='' CmdOff='' CmdOffHTTP='' CmdOffPost='' Analog='false' Repeat='0' RepeatRate='0'/>
<VirtualOutCmd Title='Volume 97' Comment='' CmdOnMethod='GET' CmdOffMethod='GET' CmdOn='\x00\x00\x02\x00\x40\x00\x00\x00\x00\x02\x39\x37' CmdOnHTTP='' CmdOnPost='' CmdOff='' CmdOffHTTP='' CmdOffPost='' Analog='false' Repeat='0' RepeatRate='0'/>
<VirtualOutCmd Title='Volume 98' Comment='' CmdOnMethod='GET' CmdOffMethod='GET' CmdOn='\x00\x00\x02\x00\x40\x00\x00\x00\x00\x02\x39\x38' CmdOnHTTP='' CmdOnPost='' CmdOff='' CmdOffHTTP='' CmdOffPost='' Analog='false' Repeat='0' RepeatRate='0'/>
<VirtualOutCmd Title='Volume 99' Comment='' CmdOnMethod='GET' CmdOffMethod='GET' CmdOn='\x00\x00\x02\x00\x40\x00\x00\x00\x00\x02\x39\x39' CmdOnHTTP='' CmdOnPost='' CmdOff='' CmdOffHTTP='' CmdOffPost='' Analog='false' Repeat='0' RepeatRate='0'/>
<VirtualOutCmd Title='Volume 100' Comment='' CmdOnMethod='GET' CmdOffMethod='GET' CmdOn='\x00\x00\x02\x00\x40\x00\x00\x00\x00\x03\x31\x30\x30' CmdOnHTTP='' CmdOnPost='' CmdOff='' CmdOffHTTP='' CmdOffPost='' Analog='false' Repeat='0' RepeatRate='0'/>